{
  "0": "ask_agri_mechanization",
  "1": "ask_agri_mechanization_apply",
  "2": "ask_agri_mechanization_details",
  "3": "ask_agri_mechanization_documents",
  "4": "ask_agri_mechanization_eligibility",
  "5": "ask_auto_pump_control",
  "6": "ask_auto_pump_control_apply",
  "7": "ask_auto_pump_control_details",
  "8": "ask_auto_pump_control_documents",
  "9": "ask_auto_pump_control_eligibility",
  "10": "ask_electric_pumps",
  "11": "ask_electric_pumps_apply",
  "12": "ask_electric_pumps_details",
  "13": "ask_electric_pumps_documents",
  "14": "ask_electric_pumps_eligibility",
  "15": "ask_integrated_development",
  "16": "ask_integrated_development_apply",
  "17": "ask_integrated_development_details",
  "18": "ask_integrated_development_documents",
  "19": "ask_integrated_development_eligibility",
  "20": "ask_land_development",
  "21": "ask_land_development_apply",
  "22": "ask_land_development_details",
  "23": "ask_land_development_documents",
  "24": "ask_land_development_eligibility",
  "25": "ask_micro_irrigation",
  "26": "ask_micro_irrigation_apply",
  "27": "ask_micro_irrigation_details",
  "28": "ask_micro_irrigation_documents",
  "29": "ask_micro_irrigation_eligibility",
  "30": "ask_pm_kisan",
  "31": "ask_pm_kisan_apply",
  "32": "ask_pm_kisan_details",
  "33": "ask_pm_kisan_documents",
  "34": "ask_pm_kisan_eligibility",
  "35": "ask_solar_dryers",
  "36": "ask_solar_dryers_apply",
  "37": "ask_solar_dryers_details",
  "38": "ask_solar_dryers_documents",
  "39": "ask_solar_dryers_eligibility",
  "40": "ask_solar_fencing",
  "41": "ask_solar_fencing_apply",
  "42": "ask_solar_fencing_details",
  "43": "ask_solar_fencing_documents",
  "44": "ask_solar_fencing_eligibility",
  "45": "ask_solar_pumps",
  "46": "ask_solar_pumps_apply",
  "47": "ask_solar_pumps_details",
  "48": "ask_solar_pumps_documents",
  "49": "ask_solar_pumps_eligibility",
  "50": "ask_sugarcane_machinery",
  "51": "ask_sugarcane_machinery_apply",
  "52": "ask_sugarcane_machinery_details",
  "53": "ask_sugarcane_machinery_documents",
  "54": "ask_sugarcane_machinery_eligibility",
  "55": "ask_value_addition",
  "56": "ask_value_addition_apply",
  "57": "ask_value_addition_details",
  "58": "ask_value_addition_documents",
  "59": "ask_value_addition_eligibility",
  "60": "ask_water_modernization",
  "61": "ask_water_modernization_apply",
  "62": "ask_water_modernization_details",
  "63": "ask_water_modernization_documents",
  "64": "ask_water_modernization_eligibility",
  "65": "goodbye",
  "66": "greet",
  "67": "set_language"
}